{
  "date": "2026-05-07",
  "generatedAt": "2026-05-07T08:44:50.818Z",
  "timestamp": 1778143490818,
  "categories": {
    "Politics": [
      {
        "headline": "FBI raids Virginia state senator's office in possible corruption probe",
        "detail": "The FBI raided the office of a Virginia state senator in a possible corruption probe. The investigation is ongoing, and details are still emerging.",
        "source": "Fox News",
        "url": "https://vertexaisearch.cloud.google.com/grounding-api-redirect/AUZIYQGNrZoUVh4N3LeP1ZkygpDtBKr_5IpSfFCsE3VM9HGnhKBYYaLQN7TolCZJLfpn4ZsXoegsmYe1kCqEX3nZoUuJeW5MmPpbBAIgBDxUIU2aOpSnc0473sVIynnB",
        "category": "Politics",
        "id": "68jjldas77r",
        "fetchedAt": "2026-05-07T02:00:12.403Z",
        "date": "2026-05-07"
      },
      {
        "headline": "Court releases purported suicide note from Jeffrey Epstein",
        "detail": "A note discovered by Jeffrey Epstein's former cellmate, purported to be a suicide note, has been released by the court after being under seal for years. However, no court or investigative agency has verified its authenticity.",
        "source": "The Washington Post",
        "url": "https://vertexaisearch.cloud.google.com/grounding-api-redirect/AUZIYQHgbZ8xo5I6rMoaGKT-OlhBvuCuCXpsqcR4CYubf6EHQPBUDJgfH2ELGDUVPW1GSjnKFQmNSx9bgG2i5YCNoEOpH5kNUWxsfFZLyMV50o2Mu_ZMELtqqShds9bvRiLVL8XskTU=",
        "category": "Politics",
        "id": "ozpuo1wapt",
        "fetchedAt": "2026-05-07T02:00:12.403Z",
        "date": "2026-05-07"
      },
      {
        "headline": "Four killed in post-election violence in India's West Bengal",
        "detail": "Following recent elections, violence in West Bengal, India has resulted in the deaths of four people. The situation remains tense in the region.",
        "source": "Al Jazeera",
        "url": "https://vertexaisearch.cloud.google.com/grounding-api-redirect/AUZIYQGDg8rWM82_2YEi_pFx1I5dL7c4mAHtubLHssPVSs1rjDmurWIRKy79L_O-DeX0kZEJF65eD9mKiZG3QuIJvh6uoVI9lpMMrb4N3HAxpNSmbo7YMPjo9d_HCNRjeh-G9pyAfQ==",
        "category": "Politics",
        "id": "91tw1r09rcs",
        "fetchedAt": "2026-05-07T02:00:12.403Z",
        "date": "2026-05-07"
      },
      {
        "headline": "Trump's mandatory detention policy fails in Florida appeals court",
        "detail": "A federal appeals court in Florida struck down the Trump administration's mandatory detention policy. The ruling is the latest legal challenge to the policy of holding people in immigration detention without the possibility of bond.",
        "source": "Axios",
        "url": "https://vertexaisearch.cloud.google.com/grounding-api-redirect/AUZIYQFBQue-mdeB0hxTUzmQ-yjyq34YCiIZeJq3kDdq_JGpdReNrS1uI7Tu0WOYT254_T10HvhmU-16yUTXxx-6-UsMM1DRUsewEOvYiugho62ky5I=",
        "category": "Politics",
        "id": "65kygoh48ky",
        "fetchedAt": "2026-05-07T02:00:12.403Z",
        "date": "2026-05-07"
      },
      {
        "headline": "UCLA medical school illegally used race in admissions, justice department finds",
        "detail": "The Justice Department has found that the UCLA medical school illegally used race in its admissions process. Further details about the findings are expected to be released.",
        "source": "The Guardian",
        "url": "https://vertexaisearch.cloud.google.com/grounding-api-redirect/AUZIYQHnQ4yBod7yJf18hTn1A8MVwlI9nTKYHNz1X8rx1Cdw0zefcEic75j9duoAnTDbzUVWKa8K_nrPz9xPB5WolBK4rccpc-0koIh9bMTmG1yL6-v_1sIgxMdTL_Wuo0iBh71xM12iioSdfJtM",
        "category": "Politics",
        "id": "p0agcmcqn1",
        "fetchedAt": "2026-05-07T02:00:12.403Z",
        "date": "2026-05-07"
      }
    ],
    "Finance & Economy": [
      {
        "headline": "India's total exports hit record $863 billion in FY26, services surge 8.7%",
        "detail": "India's total exports reached a record high of $863 billion in fiscal year 2026, with services experiencing a significant surge of 8.7%.",
        "source": "The Economic Times",
        "url": "https://economictimes.indiatimes.com/",
        "category": "Finance & Economy",
        "id": "kd8fv1jzj5d",
        "fetchedAt": "2026-05-07T02:00:28.541Z",
        "date": "2026-05-07"
      },
      {
        "headline": "Four in five Britons worried Iran war will make food more expensive, poll finds",
        "detail": "A recent poll indicates that 80% of Britons are concerned that a potential war involving Iran could lead to increased food prices.",
        "source": "The Guardian",
        "url": "https://www.theguardian.com/business",
        "category": "Finance & Economy",
        "id": "3xlzq06i672",
        "fetchedAt": "2026-05-07T02:00:28.541Z",
        "date": "2026-05-07"
      },
      {
        "headline": "Foreclosure filings hit 6-year high as costs strain American homeowners",
        "detail": "The number of foreclosure filings in the United States has reached a six-year high, signaling increasing financial strain on homeowners due to rising costs.",
        "source": "Fox Business",
        "url": "https://www.foxbusiness.com/",
        "category": "Finance & Economy",
        "id": "s4fkd02r5jd",
        "fetchedAt": "2026-05-07T02:00:28.541Z",
        "date": "2026-05-07"
      },
      {
        "headline": "Market Outlook: AI optimism pushes S&P 500 to fresh record highs",
        "detail": "Optimism surrounding artificial intelligence (AI) is driving the S&P 500 to new record highs, reflecting investor confidence in the sector's growth potential.",
        "source": "BNN Bloomberg",
        "url": "https://www.bnnbloomberg.ca/",
        "category": "Finance & Economy",
        "id": "40511kbvwqj",
        "fetchedAt": "2026-05-07T02:00:28.541Z",
        "date": "2026-05-07"
      },
      {
        "headline": "Honda more definitively halting $15B EV plant development in Ontario, according to reports",
        "detail": "Reports suggest that Honda Motor is halting the development of its $15 billion electric vehicle complex in Ontario, although Honda Canada has not confirmed this.",
        "source": "CBC News",
        "url": "https://www.cbc.ca/news/business",
        "category": "Finance & Economy",
        "id": "1llw6574ixb",
        "fetchedAt": "2026-05-07T02:00:28.541Z",
        "date": "2026-05-07"
      }
    ],
    "Technology": [
      {
        "headline": "Starlink Drops Price As Low As $29/Month to Win Over New Users",
        "detail": "Starlink is offering a discount that lowers the monthly price to $29 for the first three months of a Residential subscription, aiming to attract new users.",
        "source": "PCMag",
        "url": "https://vertexaisearch.cloud.google.com/grounding-api-redirect/AUZIYQGoGE19AUHXvbGt5me7QhOjKkx6gHnB_46b9Apq9aE3DvA0zIHbrOaFPIeGA5d90RbBKrr5vINx5ORX5mLKKgI9vyvtm3qDzANk2k57fLzvQFwXvqoi",
        "category": "Technology",
        "id": "wesffd5aep",
        "fetchedAt": "2026-05-07T02:00:12.420Z",
        "date": "2026-05-07"
      },
      {
        "headline": "Gamers Struggle to Buy New Steam Controller, Valve Pledges Restock 'Soon'",
        "detail": "The new Steam Controller quickly sold out after orders went live, with scalpers listing the $99 device for up to $700 on eBay; Valve has promised a restock soon.",
        "source": "PCMag",
        "url": "https://vertexaisearch.cloud.google.com/grounding-api-redirect/AUZIYQGoGE19AUHXvbGt5me7QhOjKkx6gHnB_46b9Apq9aE3DvA0zIHbrOaFPIeGA5d90RbBKrr5vINx5ORX5mLKKgI9vyvtm3qDzANk2k57fLzvQFwXvqoi",
        "category": "Technology",
        "id": "8gn16naqr74",
        "fetchedAt": "2026-05-07T02:00:12.420Z",
        "date": "2026-05-07"
      },
      {
        "headline": "Utah Takes Aim at VPNs With New Age-Verification Law",
        "detail": "A new law in Utah targets minors using VPNs to access porn sites, requiring age verification, but critics worry about unintended consequences due to its vague wording.",
        "source": "PCMag",
        "url": "https://vertexaisearch.cloud.google.com/grounding-api-redirect/AUZIYQGoGE19AUHXvbGt5me7QhOjKkx6gHnB_46b9Apq9aE3DvA0zIHbrOaFPIeGA5d90RbBKrr5vINx5ORX5mLKKgI9vyvtm3qDzANk2k57fLzvQFwXvqoi",
        "category": "Technology",
        "id": "332zqhbwxjj",
        "fetchedAt": "2026-05-07T02:00:12.420Z",
        "date": "2026-05-07"
      },
      {
        "headline": "Your Xbox Won't Get Microsoft Copilot AI Features After All",
        "detail": "Microsoft's Copilot AI features will not be coming to Xbox, as confirmed by Xbox's new CEO, stating that it doesn't align with the brand's direction.",
        "source": "PCMag",
        "url": "https://vertexaisearch.cloud.google.com/grounding-api-redirect/AUZIYQGoGE19AUHXvbGt5me7QhOjKkx6gHnB_46b9Apq9aE3DvA0zIHbrOaFPIeGA5d90RbBKrr5vINx5ORX5mLKKgI9vyvtm3qDzANk2k57fLzvQFwXvqoi",
        "category": "Technology",
        "id": "615zu9ymml4",
        "fetchedAt": "2026-05-07T02:00:12.420Z",
        "date": "2026-05-07"
      },
      {
        "headline": "Genetic 'bonus material' boosts gut bacterium's oxygen tolerance up to 1,000-fold",
        "detail": "Recent research has uncovered how genetic 'bonus material' can significantly enhance a gut bacterium's ability to tolerate oxygen.",
        "source": "Phys.org",
        "url": "https://vertexaisearch.cloud.google.com/grounding-api-redirect/AUZIYQFqtaVUpOcFLV6TadbBdUYZXPPDhO26aBzxAlM2Q569ONSbng255T7OaJvRSrSvD3oRdOGQs1k9LODfhmG-ADxPT48WUgGTVx5XxwGw",
        "category": "Technology",
        "id": "2pu5na5l98e",
        "fetchedAt": "2026-05-07T02:00:12.420Z",
        "date": "2026-05-07"
      }
    ],
    "Science": [
      {
        "headline": "Controlled peanut intake may reduce allergies in toddlers",
        "detail": "Researchers at Karolinska Institutet have successfully treated children aged 1–3 years with peanut allergies by gradually increasing their daily peanut consumption, desensitizing their immune systems. All children who followed the protocol achieved the goal of eating three and a half peanuts without experiencing an allergic reaction, and most were able to consume up to 25 peanuts.",
        "source": "Karolinska Institutet",
        "url": "https://vertexaisearch.cloud.google.com/grounding-api-redirect/AUZIYQFHxinItVoDjM9iCKibHA39_e-_t6xTCLLoTyRYIRDUp-4qxl5faGc_M9UwfdKk98CLYQ--U9nf8MxSirFwFyELZzVD4jjYsfjVdjM9j4HQ_rmkCGTUvHyqBIWI3q_dY6X2VVRQrUAkurXBFpCXAbyBLaCYXLUmgWMK0uCcVVv_VIkyvUCw-J8=",
        "category": "Science",
        "id": "qqmdli8ogz",
        "fetchedAt": "2026-05-07T02:00:13.254Z",
        "date": "2026-05-07"
      },
      {
        "headline": "Microsoft's Climate Goals Under AI Pressure",
        "detail": "Microsoft is reportedly considering delaying or abandoning its 2030 goal of matching its entire hourly electricity use with renewable energy purchases because the expensive and energy-intensive push for data centers is reshaping the feasibility of Microsoft's climate commitments that were made before the AI era. Like rivals Amazon and Alphabet, the Windows maker is spending hundreds of billions of dollars to build out artificial intelligence infrastructure needed to power services such as its Copilot assistant and Azure cloud service.",
        "source": "CommonWealth Magazine",
        "url": "https://vertexaisearch.cloud.google.com/grounding-api-redirect/AUZIYQHJe2BRPCfcTD7nnTlnZa_HIZ5wui_O80RygJRUOQFzmhML7lqBKNv5SsmXojvHuvaYF6fm6tT286RGWtSjWAGKws3T24KRGCW9YlCxS05K-qsmxFvxDsTVYIonj1z_5GMzSC48hpUFjz74i5jAxuEFp1dw",
        "category": "Science",
        "id": "y0myajnjcrf",
        "fetchedAt": "2026-05-07T02:00:13.254Z",
        "date": "2026-05-07"
      },
      {
        "headline": "Dynamic catalyst interfaces offer a smarter route for converting CO₂ into formic acid",
        "detail": "A new study explores dynamic catalyst interfaces as a smarter way to convert CO₂ into formic acid. This approach may offer a more efficient and sustainable method for producing this valuable chemical.",
        "source": "Phys.org",
        "url": "https://vertexaisearch.cloud.google.com/grounding-api-redirect/AUZIYQGLXRyhSaaMduIVQyCibYMZ6NdVXHR_tvq0hMia_OHdyaR49G6EMLGalWNeLjMKJ1xXwVA2weXCC5A4-ZPE63PHTI08YimDVMQpzFor",
        "category": "Science",
        "id": "7mlx3k5sd",
        "fetchedAt": "2026-05-07T02:00:13.254Z",
        "date": "2026-05-07"
      },
      {
        "headline": "Human language shows deep safety bias, challenging 70-year scientific consensus",
        "detail": "A recent study challenges a 70-year scientific consensus by revealing a deep safety bias in human language. This finding suggests that our communication is inherently geared towards prioritizing safety and avoiding potential threats.",
        "source": "Phys.org",
        "url": "https://vertexaisearch.cloud.google.com/grounding-api-redirect/AUZIYQGLXRyhSaaMduIVQyCibYMZ6NdVXHR_tvq0hMia_OHdyaR49G6EMLGalWNeLjMKJ1xXwVA2weXCC5A4-ZPE63PHTI08YimDVMQpzFor",
        "category": "Science",
        "id": "42uam2yku7m",
        "fetchedAt": "2026-05-07T02:00:13.254Z",
        "date": "2026-05-07"
      },
      {
        "headline": "New long-necked dinosaur found in Northeast Brazil was a close relative of a European species.",
        "detail": "A newly discovered long-necked dinosaur in Northeast Brazil has been identified as a close relative of a European species. This finding provides insights into the connections between dinosaur populations across different continents.",
        "source": "Phys.org",
        "url": "https://vertexaisearch.cloud.google.com/grounding-api-redirect/AUZIYQGLXRyhSaaMduIVQyCibYMZ6NdVXHR_tvq0hMia_OHdyaR49G6EMLGalWNeLjMKJ1xXwVA2weXCC5A4-ZPE63PHTI08YimDVMQpzFor",
        "category": "Science",
        "id": "odv23nzj1d",
        "fetchedAt": "2026-05-07T02:00:13.254Z",
        "date": "2026-05-07"
      }
    ],
    "Health": [
      {
        "headline": "International Health Alert: Hantavirus Cases on Cruise Ship Rise to Five",
        "detail": "The World Health Organization (WHO) has announced an increase in confirmed Hantavirus cases linked to a cruise ship, bringing the total to five, and has raised its alert level to address this limited outbreak. Two additional passengers were evacuated for treatment at specialized medical centers amid strict precautionary measures aimed at preventing the ship from becoming an epidemic hotspot.",
        "source": "Voice of Emirates News Agency",
        "url": "https://vertexaisearch.cloud.google.com/grounding-api-redirect/AUZIYQGyb1NvVNoIv5TJt-_l27cemScm4N85FkSxvAWp5x16zFb7xGoBdUrmDpYOPC1IOVPfiIDhU9ubrHqCCAqwyuX8aKO4_fWB8oXrZRIIOVF4eC3_Ds8oUhm6a33_xA4khugujfOeS3VUefhoRBHJmq2RfIlYVGzVzvW-eZyv-LI3nNP-XlIRpgWuA_BsCFfEBtaVJefXNAG5ugR_LkjdtMsgvpyc4-BG3wikpZGMBEh9mGf46AeblA==",
        "category": "Health",
        "id": "n7659mm4qz",
        "fetchedAt": "2026-05-07T02:00:14.757Z",
        "date": "2026-05-07"
      },
      {
        "headline": "Hantavirus Outbreak on Cruise Ship: 3 Dead, Patients Evacuated to Europe",
        "detail": "Three people have died and eight cases have been recorded in all due to a Hantavirus outbreak on a cruise ship, according to the World Health Organization. Contact tracing has begun in Europe and Africa in search of infections around people who earlier left the ship, which departed over a month ago from South America.",
        "source": "Daily Pioneer",
        "url": "https://vertexaisearch.cloud.google.com/grounding-api-redirect/AUZIYQEY7Z9hnoE0nrDwPdocAQo7NcmVtzMKzsjlUE_GvvylbVsZdw_s1xqRvGB7ULGcDk74NOp_HdIgSrOzZoelun5uAbFiOyOzqk56HGMgybxBOLbjOCn7R9yXfs1tFbU2Q5IktxcPNihbtQUtg05tqew6-4fyAkSagjUOO2-DzKfAOR4nyGfKLIj4bhEStOVx18G56Xn0EQlld3MLNA==",
        "category": "Health",
        "id": "nreucslpji",
        "fetchedAt": "2026-05-07T02:00:14.757Z",
        "date": "2026-05-07"
      },
      {
        "headline": "Three evacuated from hantavirus-hit ship",
        "detail": "Emergency crews evacuated three people from a cruise ship stricken with a deadly outbreak of hantavirus, the WHO said, as experts confirmed a rare strain that can be transmitted between humans. Two crew members and one other person thought to be infected were being taken off the MV Hondius and will be flown to the Netherlands for treatment.",
        "source": "Taipei Times",
        "url": "https://vertexaisearch.cloud.google.com/grounding-api-redirect/AUZIYQGQDHLXnzs6ntbtai1D_mRT2xbvbqQusWzJJiy-kxtBEP0KMj7Shiu8EQaQmxXXarO20dHwkY94o4yHnaXCXbaAYfjL-i6CXREcvzOqgwRxOq0n-6KfkdWwpQxDOAKStdhKKpWm4df16J9sjWxWOaSLNq1qrngpZOoqEAfDXIO3jg==",
        "category": "Health",
        "id": "mi8monjbuym",
        "fetchedAt": "2026-05-07T02:00:14.757Z",
        "date": "2026-05-07"
      },
      {
        "headline": "Government of Canada to make an announcement on mental health support",
        "detail": "The Honourable Eleanor Olszewski, Minister of Emergency Management and Community Resilience and Minister responsible for Prairies Economic Development Canada (PrairiesCan), on behalf of the Honourable Marjorie Michel, Minister of Health, will make an announcement on mental health and psychosocial supports in emergency settings on May 7, 2026. There will be a media availability immediately following the announcement.",
        "source": "Canada.ca",
        "url": "https://vertexaisearch.cloud.google.com/grounding-api-redirect/AUZIYQEXXvT6hbvkEJwNmedYjBeLHGY701euElN1JJfCwsBsRnVWg8Sdk_eunZPaWAeGo7DPftFzankrnaLiiQVBXGWVtmMLDLYgEHUtnutAvqGOx-YbuaKnWX1swWObt0sR1omxp_y-ctIQXbHuh4BxC0dthYsoaYqbFfByEwxfHdwV8z3bMZ1E0VttNJ51HSGd97svBBR2bmrtyYVbZ3-UAhPKf1J8oO5kM0KNfzAonj-lgdN6ZB21JIQOPQ==",
        "category": "Health",
        "id": "npns589zzq",
        "fetchedAt": "2026-05-07T02:00:14.757Z",
        "date": "2026-05-07"
      },
      {
        "headline": "Mandaviya to launch nationwide free Annual Health Check-Up Initiative",
        "detail": "Union Minister of Labour & Employment Mansukh Mandaviya will launch a nationwide free 'Annual Health Check-Up Initiative' for Workers aged 40 years and above on May 7, 2026, as proposed under the new Labour Codes. The initiative will be formally inaugurated from the Employees' State Insurance Corporation (ESIC) Medical College & Hospital, Basaidarapur, New Delhi, with simultaneous launch events across 11 other ESIC hospitals.",
        "source": "Daily Pioneer",
        "url": "https://vertexaisearch.cloud.google.com/grounding-api-redirect/AUZIYQFkCWr5SVN2tftMOTcLcxfkSt2S7SsH6qPHGkxGkv_Q-PYr7_So9lqDs1LZyS9bOhVRzocOWZg3CwJb3SYHiFGc-0BT3THrvLSOYgkGCoZ-I3HEFfSyHy3Wi4M5iJjOL3OIG0QFxcnQ2Y-OJmL9_UYsarF3OxJrfzbDAUp1_nVqLZgDfB9ULvW3JPvO3k_WGkOrWzoyf-b38tElcmf25DFjh6eWXmLjls5C6jLa5xVGk6fJ",
        "category": "Health",
        "id": "mzfb7e5ayx",
        "fetchedAt": "2026-05-07T02:00:14.757Z",
        "date": "2026-05-07"
      }
    ],
    "Sports": [
      {
        "headline": "PSG hold off Bayern to book final showdown with Arsenal",
        "detail": "Paris Saint-Germain advanced to the Champions League final after a 1-1 draw against Bayern Munich, setting up a final match against Arsenal. The match was tightly contested, with PSG ultimately securing their spot on aggregate.",
        "source": "The Guardian",
        "url": "https://vertexaisearch.cloud.google.com/grounding-api-redirect/AUZIYQHqnKx-CStC9ge1BWBBX02rziLpOBLMtLuhCyP4ugan4KfozpdeualLJGHayS7-ZeW2NvzsoK3GOn6NveTvm5sF06eTdwtwVXB2cQQEFoYk-ImXlIkXa5-RcMXFHShhhA==",
        "category": "Sports",
        "id": "ixs7n7du1mc",
        "fetchedAt": "2026-05-07T02:00:12.191Z",
        "date": "2026-05-07"
      },
      {
        "headline": "Man City clinches Women's Super League title to end Chelsea's dominance",
        "detail": "Manchester City has won the Women's Super League title, bringing an end to Chelsea's recent dominance in the league. The victory marks a significant achievement for Man City and a shift in the landscape of women's soccer in England.",
        "source": "AP News",
        "url": "https://vertexaisearch.cloud.google.com/grounding-api-redirect/AUZIYQEHoLI7dIxArR5uPTcjtZkpKTSx1oYJ2Pzepbd0vkckhzFOIv0rE3LZmQgiu2KJ5YZgWAWTvcRI0k8FMvimQr5tMQhAhgzrm3lqqO6qxoQgoEZKIYg=",
        "category": "Sports",
        "id": "samdz1f5y1",
        "fetchedAt": "2026-05-07T02:00:12.191Z",
        "date": "2026-05-07"
      },
      {
        "headline": "Runner dies after medical emergency during 253-mile ultramarathon",
        "detail": "A runner tragically passed away after experiencing a medical emergency during a 253-mile ultramarathon in Arizona. The incident highlights the extreme challenges and risks associated with such endurance events.",
        "source": "The Guardian",
        "url": "https://vertexaisearch.cloud.google.com/grounding-api-redirect/AUZIYQHqnKx-CStC9ge1BWBBX02rziLpOBLMtLuhCyP4ugan4KfozpdeualLJGHayS7-ZeW2NvzsoK3GOn6NveTvm5sF06eTdwtwVXB2cQQEFoYk-ImXlIkXa5-RcMXFHShhhA==",
        "category": "Sports",
        "id": "7ekg59mnhyh",
        "fetchedAt": "2026-05-07T02:00:12.191Z",
        "date": "2026-05-07"
      },
      {
        "headline": "Joel Embiid is out for Game 2 of the 76ers' series against the Knicks with ankle and hip injuries",
        "detail": "Joel Embiid will miss Game 2 of the 76ers' series against the Knicks due to ankle and hip injuries. This absence is a significant blow to the 76ers' chances as they face a tough opponent in the playoffs.",
        "source": "AP News",
        "url": "https://vertexaisearch.cloud.google.com/grounding-api-redirect/AUZIYQEHoLI7dIxArR5uPTcjtZkpKTSx1oYJ2Pzepbd0vkckhzFOIv0rE3LZmQgiu2KJ5YZgWAWTvcRI0k8FMvimQr5tMQhAhgzrm3lqqO6qxoQgoEZKIYg=",
        "category": "Sports",
        "id": "y8kwwrnldk",
        "fetchedAt": "2026-05-07T02:00:12.191Z",
        "date": "2026-05-07"
      },
      {
        "headline": "Kentucky Derby winner Golden Tempo is not running in the Preakness",
        "detail": "Golden Tempo, the winner of the Kentucky Derby, will not be participating in the Preakness Stakes. The decision alters the landscape of the race and opens up opportunities for other contenders.",
        "source": "AP News",
        "url": "https://vertexaisearch.cloud.google.com/grounding-api-redirect/AUZIYQEHoLI7dIxArR5uPTcjtZkpKTSx1oYJ2Pzepbd0vkckhzFOIv0rE3LZmQgiu2KJ5YZgWAWTvcRI0k8FMvimQr5tMQhAhgzrm3lqqO6qxoQgoEZKIYg=",
        "category": "Sports",
        "id": "0c5hbftd5slk",
        "fetchedAt": "2026-05-07T02:00:12.191Z",
        "date": "2026-05-07"
      }
    ],
    "Entertainment": [
      {
        "headline": "Ted Turner Dies: CNN Founder Dead at 87",
        "detail": "Media mogul and CNN founder, Ted Turner, has passed away at the age of 87. Turner transformed the media landscape and was a global media titan.",
        "source": "Hollywood Life",
        "url": "https://vertexaisearch.cloud.google.com/grounding-api-redirect/AUZIYQGkk_NyBYOadyb2JgJde2XWE6BIgFgYx6vc4JG14s7RDER5sDKeLp-8SDUeDET7NI6UDrxLCB25rt-h7cYWVVE303PLjL1en3xbyOVuuM-1RhjqL_cY",
        "category": "Entertainment",
        "id": "j4d25bx3ij",
        "fetchedAt": "2026-05-07T02:00:13.010Z",
        "date": "2026-05-07"
      },
      {
        "headline": "Matthew Perry's belongings to be auctioned as Friends memorabilia and original Banksy up for sale",
        "detail": "Items belonging to the late actor Matthew Perry, including Friends memorabilia, are going up for auction. The auction also features an original Banksy artwork.",
        "source": "Guardian US",
        "url": "https://vertexaisearch.cloud.google.com/grounding-api-redirect/AUZIYQEdwa8NFd8Pub244llDKf8KDvYQ46U7YjDSdRv4_1JB6XnDBDsAkfCqIkvByDUKr89PCBWRGzhrXHVUeTvxssq7F4CrAyI15dTCVfzV6hvtOpx_R7lyfLYISVq5lQ3Pd6__",
        "category": "Entertainment",
        "id": "1o89ypn7mnb",
        "fetchedAt": "2026-05-07T02:00:13.010Z",
        "date": "2026-05-07"
      },
      {
        "headline": "Blake Lively Emails Show Spiraling Over 'It Ends With Us' Backlash",
        "detail": "Emails reveal Blake Lively's distress over the backlash surrounding the film adaptation of 'It Ends With Us'. The dispute between Lively and Justin Baldoni has been settled.",
        "source": "TMZ",
        "url": "https://vertexaisearch.cloud.google.com/grounding-api-redirect/AUZIYQFA1Vpw4OY4wd_uu7c8ofuEvrP-mq91aGMnjYrNiIJQAX_cypxYkPjbmI1ZOcx9psxj7HWhGEWW26WeHunc7ez9VOz8ePA6JPjHQh0jgSNs",
        "category": "Entertainment",
        "id": "i9vng9a0guc",
        "fetchedAt": "2026-05-07T02:00:13.010Z",
        "date": "2026-05-07"
      },
      {
        "headline": "Rihanna Looks Unhappy as A$AP Rocky Chats With Woman at Met Gala",
        "detail": "Photos suggest Rihanna appeared unhappy while A$AP Rocky was conversing with another woman at the Met Gala. This sparked rumors and speculation.",
        "source": "TMZ",
        "url": "https://vertexaisearch.cloud.google.com/grounding-api-redirect/AUZIYQFA1Vpw4OY4wd_uu7c8ofuEvrP-mq91aGMnjYrNiIJQAX_cypxYkPjbmI1ZOcx9psxj7HWhGEWW26WeHunc7ez9VOz8ePA6JPjHQh0jgSNs",
        "category": "Entertainment",
        "id": "fv6di26aftd",
        "fetchedAt": "2026-05-07T02:00:13.010Z",
        "date": "2026-05-07"
      },
      {
        "headline": "Bill Cosby Found Liable in Sexual Assault Case, Owes Victim $59M",
        "detail": "Bill Cosby has been found liable in a sexual assault case and ordered to pay $59 million in damages to Donna Motsinger for drugging and assaulting her in 1972.",
        "source": "Entertainment Tonight",
        "url": "https://vertexaisearch.cloud.google.com/grounding-api-redirect/AUZIYQEbAWZP_ZuuWZi_WczL8CWENhv-Wh69wQCzz1a7hJ3V4QV8UbzFl-LdlmQZYiMfDUEEBmvE54unoM5CiDnl0z4UBfxgJbUNdVkwaLyK6-vgMW0k7skAu0_z",
        "category": "Entertainment",
        "id": "aajk6e31qqb",
        "fetchedAt": "2026-05-07T02:00:13.010Z",
        "date": "2026-05-07"
      }
    ],
    "Crime & Justice": [
      {
        "headline": "Child protection workers stood down after Alice Springs girl's death",
        "detail": "Three child protection workers have been stood down after it was revealed multiple welfare reports were raised about a young girl before her alleged murder in Alice Springs, Australia; a man has been charged with the 5-year-old's murder, spurring riots and calls for a review of conditions within town camps.",
        "source": "1News",
        "url": "https://vertexaisearch.cloud.google.com/grounding-api-redirect/AUZIYQHg66NlBfUHjO4s8aqGceVxnNWZaWqV5-v4TgmJS_5ETyfGODjAQfNBjUMOSRLEaCQ9pYupY6b_z0mt8GTfxUouR1GzU4-VQK4pBYsD419iXqfwjPHLYI1FFOL43eowaBVJQYMCTGuoBaWtlMOklnJdHi7REpPYtDO-4Ja1z3Fw-LDNSrZv3nGWfUeyPJcDb6Lmz9aLCgWn2EEqioSvTvRMztE=",
        "category": "Crime & Justice",
        "id": "zou7dgstjn",
        "fetchedAt": "2026-05-07T02:00:22.254Z",
        "date": "2026-05-07"
      },
      {
        "headline": "Suspect arrested in Oklahoma party shooting that killed 1, injured 22",
        "detail": "Police have arrested an 18-year-old in connection with a shooting at a party in Oklahoma that resulted in one death and 22 injuries.",
        "source": "CBS News",
        "url": "https://vertexaisearch.cloud.google.com/grounding-api-redirect/AUZIYQGkO2bya4yvOkjm7As32BAaGn7Zt50KvM88FP4BJeQ8KtWu5gunTBR2OyeIY5ZPkmo9jmYosZSl1vzXqgrTevW3y2Ruhalv-QrMz6avZ1evEIBQJezCPvDTRQ==",
        "category": "Crime & Justice",
        "id": "4q5endjojxl",
        "fetchedAt": "2026-05-07T02:00:22.254Z",
        "date": "2026-05-07"
      },
      {
        "headline": "Justice Department Announces Results of Operation Iron Pursuit",
        "detail": "The Justice Department announced the results of Operation Iron Pursuit.",
        "source": "FBI",
        "url": "https://vertexaisearch.cloud.google.com/grounding-api-redirect/AUZIYQH2gfsqjMZUkStrvXkeKgsv39pTNnBDC1Fj_hXrUrQ8pZ7izJChzC9CSubY60pEJ3qwAdjLsRsgUrZyfoRGzCqIA3ASZUmXhkfEwu4Rnllfs8QC4Dvo2_PHGaMRrMac4SSIWaAS0Uerbwa-jPQU",
        "category": "Crime & Justice",
        "id": "kx788c9ab4q",
        "fetchedAt": "2026-05-07T02:00:22.254Z",
        "date": "2026-05-07"
      },
      {
        "headline": "Correspondents' dinner suspect faces new charge of assaulting federal officer",
        "detail": "Cole Allen, who is accused of targeting Trump, faces a revised indictment alleging he assaulted a federal officer with a deadly weapon.",
        "source": "The Guardian",
        "url": "https://vertexaisearch.cloud.google.com/grounding-api-redirect/AUZIYQE8UamEqGcwEEKmg1MBScfB0s9-yUqqd8HEa7-INXw8XtYQJ7m8938Na56qkrlzcrm-gNE9MDRn649FByhyiVE2_F0wW6qPzpNOR-4MuBiTZPmZOtTYjmd7v84ODopaBA1EyvFzktUF",
        "category": "Crime & Justice",
        "id": "xfsb2swb4v",
        "fetchedAt": "2026-05-07T02:00:22.254Z",
        "date": "2026-05-07"
      },
      {
        "headline": "Palm Beach County Sheriff's deputy behind bars accused of kidnapping and other crimes",
        "detail": "A Palm Beach County Sheriff's deputy has been arrested and is accused of kidnapping, while two other members of the sheriff's office were also arrested on fraud charges.",
        "source": "YouTube - WPBF 25 News",
        "url": "https://vertexaisearch.cloud.google.com/grounding-api-redirect/AUZIYQHmOdNtMABc2105XyHL9pSuVxY1rtFfPvoJsFZV4FIL01_9LIyfdwb67ikI-4cktijfUTtsmrVZ3TNqgehQQH0dZOy9MGqkr56RKGBwSc2OUN4_uRWaxXaSjRfsnXaaCrvwSLNJ4s0=",
        "category": "Crime & Justice",
        "id": "zsxeyvox0k9",
        "fetchedAt": "2026-05-07T02:00:22.254Z",
        "date": "2026-05-07"
      }
    ],
    "Education": [
      {
        "headline": "Schools must comply with existing safety guidelines to strengthen school safety standards, says Education Ministry",
        "detail": "The Education Ministry in Malaysia expressed concern over recent accidents in schools and stated that all schools must comply with the existing Safe School Management Guidelines currently in force. The statement follows recent fatal crash incidents at schools, highlighting the need to strengthen school safety.",
        "source": "The Star",
        "url": "https://vertexaisearch.cloud.google.com/grounding-api-redirect/AUZIYQGSLC8vAdrOraBseCBOsPGrWQenO6BW9v7YC0PEDsGAxvmXd7NdRmOqr9DUdnnm4BaDOqcQJ4UbCPaxSXtvV2r9uqVTVYOVW_CukQHvv4aodrIhqXk3t13CbHO90cVTm913G1e9V6bUxDVOLXPV3EbomI_pQ21z0iAdcKMbUqN7Sudq3X2ROjnJLcUQQD3ofDfSONi3j94VV8b4shYxDEF6SFbBkdzFHBB8UecyRZYy-0z4MN5RdQB-rmXxmshU4DPTkjxzbFhd5ADCWinqmA5ayPTunf9zCanDePxMsazQ",
        "category": "Education",
        "id": "h0fyicsjgx",
        "fetchedAt": "2026-05-07T02:00:23.532Z",
        "date": "2026-05-07"
      },
      {
        "headline": "How These Schools Doubled Teacher Planning Time",
        "detail": "Alliance charter network schools have doubled daily teacher planning time to 8-12 hours per week, which has improved teacher retention and student performance. Chronic absenteeism fell 2% and student performance grew nearly 9% in English/language arts and by more than 36% in math in the pilot schools.",
        "source": "Education Week",
        "url": "https://vertexaisearch.cloud.google.com/grounding-api-redirect/AUZIYQG_5_Yel_uXBr0JK68OH4Nc36XcYMpREEcv4K0kLI6PwSH8TmRNraWeXUoIl3j77rsyLx09kl-YOTF4rjUlRQsduM0kHaieWN_AQ9rQ9UzA2rX9Xs1R2s6nRZw08ftvTjuK_nXu0rYLuW2kyKFzvdRO6vzT_YM82AEZNZukYTAabfu3bydkzvGKpmUIFNGFalfhhEoQ",
        "category": "Education",
        "id": "77wkuo9hcno",
        "fetchedAt": "2026-05-07T02:00:23.532Z",
        "date": "2026-05-07"
      },
      {
        "headline": "Tomorrow's Teachers Sign On to Shape the Future",
        "detail": "College and high school students in Connecticut were celebrated for their choice to enter the teaching profession at a Signing Day and Apprenticeship Graduation for Educators Rising event. The program is supported by the Connecticut State Department of Education, Department of Labor, Connecticut Education Association, and other state agencies and organizations, aiming to nurture the love of teaching early and support students through major milestones.",
        "source": "Connecticut Education Association",
        "url": "https://vertexaisearch.cloud.google.com/grounding-api-redirect/AUZIYQFMwjiL5pusQaaYxIRsugpd6MkEz81Wyntk2R96OeBN2TPGvyKYUo2G011OoQh49n28g4_0XR2BNX_xG-hoK4KG85HAsJrQkliku9pXOkEjSq81B1j75csO_I9q_GvpScri4f_VjISJVTYn9hHrIysLD7kpkw51ZyrHEw==",
        "category": "Education",
        "id": "klbgdj9ea3a",
        "fetchedAt": "2026-05-07T02:00:23.532Z",
        "date": "2026-05-07"
      },
      {
        "headline": "Palestinian ambassador protests to Foreign Office over 'erasure' by British Museum",
        "detail": "The Palestinian ambassador has formally protested to the Foreign Office regarding perceived 'erasure' by the British Museum. Details of the specific issue prompting the protest were not elaborated upon in the search results.",
        "source": "The Guardian",
        "url": "https://vertexaisearch.cloud.google.com/grounding-api-redirect/AUZIYQHMh18-gIpUmnHe_ViLEHe5GTgQ40Y8aJnauFU51rnmK_mAMugffWunmAd_8ESew9OV1WRK1rHgRZrko0NBypbV7Aea83rQ-W196swqPF0Djk2i7fyOVZ8uRvH_gnfQeO2MunBdrlA3q4pru_VWuZGD6uUKrMES",
        "category": "Education",
        "id": "wcy6p1dlria",
        "fetchedAt": "2026-05-07T02:00:23.532Z",
        "date": "2026-05-07"
      },
      {
        "headline": "Universities unite behind Nepal's “10k int'l student” ambition",
        "detail": "Nepalese universities are collaborating to attract international students, aiming to increase enrollment more than sixfold within three years. This initiative seeks to position Nepal as an \"emerging South Asian education destination\".",
        "source": "The PIE News",
        "url": "https://vertexaisearch.cloud.google.com/grounding-api-redirect/AUZIYQFruIpeP5OKH1Hequ3G2Kkg1-A5_lZ6hGWqcZGeEw9XD4FWGYG4h41I6Jv1Ar9pmTb_xLhTIKF12OaQhMwDZ9mOoTjXVRf6SA-cuzLkYUjzTNJ6I8ESX1w=",
        "category": "Education",
        "id": "65qbzhudcwl",
        "fetchedAt": "2026-05-07T02:00:23.532Z",
        "date": "2026-05-07"
      }
    ],
    "Lifestyle": [
      {
        "headline": "7 beloved recipes to cherish for Mother's Day and beyond",
        "detail": "Food is an important part of what many of us hope to pass on, for Mother's Day and beyond.",
        "source": "The Washington Post",
        "url": "https://vertexaisearch.cloud.google.com/grounding-api-redirect/AUZIYQGZi64KBEvGVWI81zdSNIdvl_f54eytToqDJGuqTbiIpjokR9WJgji9wyTKdZSVj0999twFfL9KJA7AEjz3XWqG9bQ1TIIwsNPQjbUzkdRZlDVIC3hIcQM66hR1YPq4o5lPSY7K",
        "category": "Lifestyle",
        "id": "i0o4argv6t",
        "fetchedAt": "2026-05-07T02:00:12.005Z",
        "date": "2026-05-07"
      },
      {
        "headline": "My teen pushed me because she wants an iPhone. Do we give in and get her one?",
        "detail": "A parent asks for advice on whether to give in to their teen's demands for an iPhone after the teen physically pushed them.",
        "source": "The Washington Post",
        "url": "https://vertexaisearch.cloud.google.com/grounding-api-redirect/AUZIYQGZi64KBEvGVWI81zdSNIdvl_f54eytToqDJGuqTbiIpjokR9WJgji9wyTKdZSVj0999twFfL9KJA7AEjz3XWqG9bQ1TIIwsNPQjbUzkdRZlDVIC3hIcQM66hR1YPq4o5lPSY7K",
        "category": "Lifestyle",
        "id": "ir21huvld9",
        "fetchedAt": "2026-05-07T02:00:12.005Z",
        "date": "2026-05-07"
      },
      {
        "headline": "A promising new depression therapy focuses on finding paths to joy.",
        "detail": "A new therapy for depression is being explored that emphasizes finding paths to joy.",
        "source": "The Washington Post",
        "url": "https://vertexaisearch.cloud.google.com/grounding-api-redirect/AUZIYQGZi64KBEvGVWI81zdSNIdvl_f54eytToqDJGuqTbiIpjokR9WJgji9wyTKdZSVj0999twFfL9KJA7AEjz3XWqG9bQ1TIIwsNPQjbUzkdRZlDVIC3hIcQM66hR1YPq4o5lPSY7K",
        "category": "Lifestyle",
        "id": "vhtgwln9t2",
        "fetchedAt": "2026-05-07T02:00:12.005Z",
        "date": "2026-05-07"
      },
      {
        "headline": "Costco is adding chicken strips to the Food Court.",
        "detail": "Costco is expanding its food court menu with the addition of chicken strips.",
        "source": "NewsNow",
        "url": "https://vertexaisearch.cloud.google.com/grounding-api-redirect/AUZIYQH-yD4uYRYhbI2906BgjD9X__ku_c028LBQ7gMW3GP-wqW5Db4mlNRDgsulg2O6zpdxgGFkFs-xwNYHc-4IVbNfN2H5v3Xy3KJiGzlpEa74PO-C6E73WrNWX00xUqV4Qw==",
        "category": "Lifestyle",
        "id": "ln3j6kfxnk",
        "fetchedAt": "2026-05-07T02:00:12.005Z",
        "date": "2026-05-07"
      },
      {
        "headline": "German Shepherd, abandoned at a California Walmart with all of his toys, gets a second chance.",
        "detail": "A German Shepherd left at a Walmart in California with his toys is getting a new home.",
        "source": "People",
        "url": "https://vertexaisearch.cloud.google.com/grounding-api-redirect/AUZIYQH-yD4uYRYhbI2906BgjD9X__ku_c028LBQ7gMW3GP-wqW5Db4mlNRDgsulg2O6zpdxgGFkFs-xwNYHc-4IVbNfN2H5v3Xy3KJiGzlpEa74PO-C6E73WrNWX00xUqV4Qw==",
        "category": "Lifestyle",
        "id": "b9vjwci43mt",
        "fetchedAt": "2026-05-07T02:00:12.005Z",
        "date": "2026-05-07"
      }
    ],
    "Opinion/Editorial": [
      {
        "headline": "Bayside Editorial: Berlin must deal with lead pipes issue now",
        "detail": "Berlin town officials must continue their pursuit of the water line replacement project along Williams Street to prevent lead from leaching into drinking water, even with funding challenges.",
        "source": "Bayside Gazette",
        "url": "https://vertexaisearch.cloud.google.com/grounding-api-redirect/AUZIYQE-E7FaVeZxLt4NMtnagb2XxsU7nC8cXuD8cjKNU3Hzbypps0pgWrv5y4P1vr-5CDQBo_DnVEqxEh52Z7fdXSGAVJvqhyrM35XU_RwIVpcFKuA5YUEbiXLXAl-4O3y2m2h8MOOIQozFA5juEjThBI-eqwIaM7pTOkch8G39Wke18ku5RZWwAMA9MSsgbLZ1yOUASDYhVpyUEkk=",
        "category": "Opinion/Editorial",
        "id": "ongan09ecj",
        "fetchedAt": "2026-05-07T02:00:14.352Z",
        "date": "2026-05-07"
      },
      {
        "headline": "EDITORIAL - Inflationary",
        "detail": "All surveys have consistently shown inflation as the top concern of Filipinos, and President Marcos is getting the lowest marks in tackling the problem as inflation surged to 7.2 percent in April.",
        "source": "Philstar.com",
        "url": "https://vertexaisearch.cloud.google.com/grounding-api-redirect/AUZIYQGRJHE1Eic1eQgr9iA04sTevenIHSntGFmnZy-3-rrimYFcOaJofND2wyH5-322_eE74dYmSQWGwoq7NzBqbK0jOcEPZjNcZIn4_Ab_zv0rjz70otqX-Hped_2eA57BiXaYE6_fuKOZAH_0VVbHq9Ova5fxe8SSECegzoOGZRF4FSunMtY7",
        "category": "Opinion/Editorial",
        "id": "tx9ku6f67z",
        "fetchedAt": "2026-05-07T02:00:14.352Z",
        "date": "2026-05-07"
      },
      {
        "headline": "Letters to The Editor — May 7, 2026",
        "detail": "The Congress party's move to support the Tamilaga Vettri Kazhagam (TVK) is troubling as it will undermine the INDIA bloc alliance, ignoring the political understanding that held the alliance together. The TVK's rise signals a public desire for political renewal, but its next steps will define its credibility.",
        "source": "The Hindu",
        "url": "https://vertexaisearch.cloud.google.com/grounding-api-redirect/AUZIYQFepsJjdZJRKcGseUHsUpXsujHpOtZtbblK5-m7XCUr2Nx14Y5dQWTHg4vzMYzg84n9WHX85V_VYietm-o68UIn2BEZ4tzOpHSn7KKClSMJuQCDNUmilGeP7gggilbJYLiPzYfoAXuwqA4Xv-t22XpYocB5nPVxT8d191ukzJqLsgmwtBAhOJj6yq-rsGqtqoeXzph6WZFVMw==",
        "category": "Opinion/Editorial",
        "id": "4yjb8oiyxp3",
        "fetchedAt": "2026-05-07T02:00:14.352Z",
        "date": "2026-05-07"
      },
      {
        "headline": "Tardy justice",
        "detail": "An editorial discusses the slow progress of justice in a case involving allegations against former President Rodrigo Duterte, highlighting concerns about delays in the legal process.",
        "source": "Inquirer.net",
        "url": "https://vertexaisearch.cloud.google.com/grounding-api-redirect/AUZIYQExV0XNJLzLFp862HJLZQIy909StuDOQLBwHJ6odhn0JalV24_5zyh2ZHeOIUriV-X48-6sSjYRDExNanfYCTpntBAzGeiKSjAe8Y16VhRA0_tLQ9gZlXET",
        "category": "Opinion/Editorial",
        "id": "5p52u1vv5ia",
        "fetchedAt": "2026-05-07T02:00:14.352Z",
        "date": "2026-05-07"
      },
      {
        "headline": "EDITORIAL: Preparing people to prevent fraud",
        "detail": "An editorial emphasizes the importance of public education and awareness to combat fraud in Taiwan, as criminals are often undeterred by long prison sentences. The government has launched anti-fraud campaigns using various media to highlight common scam tactics.",
        "source": "Taipei Times",
        "url": "https://vertexaisearch.cloud.google.com/grounding-api-redirect/AUZIYQFZCPTAz1qPiaP08mSpOCB74vTYTqAqMu0rs7cIAnB4saVbt_zoG56rnfG-DhClVsMKE5MPybWuiZZ8UUe6ehK_HG_bAJUuHR47ZL28FnGgOzC-I-adx8fy6Y4dZp_J5hmFu4C2ZmnZODmQgnwwk7wp4w2RVV1dj5K0rVH9cDpC7Du8cyf5",
        "category": "Opinion/Editorial",
        "id": "tsubrty133",
        "fetchedAt": "2026-05-07T02:00:14.352Z",
        "date": "2026-05-07"
      }
    ],
    "World": [],
    "Zimbabwe": [
      {
        "headline": "GWEKWERERE CONFIRMS BEATING HIS WIFE NATASHA AFTER ROW OVER A LOVER",
        "detail": "Details are scarce, but B-Metro reports that Gwekwerere has confirmed physically assaulting his wife, Natasha, following a dispute regarding a lover.",
        "source": "B-Metro",
        "url": "https://vertexaisearch.cloud.google.com/grounding-api-redirect/AUZIYQGAdkTk1YBnfEbRjj4PzNFuDFH0cs25ZaNVVw15gRbFqkOWxQq5dk5BPm4vTgdYwKCc-JViSGoORsBkPleubOoj2-YUf5PzxthGl1bcU37A8YjPkO6X6aBbm_Ce6CfrVzA=",
        "category": "Zimbabwe",
        "id": "00im5y3sm6ty",
        "fetchedAt": "2026-05-07T02:00:17.663Z",
        "date": "2026-05-07"
      },
      {
        "headline": "CHIVAYO EXCLUSIVE: A SCOOP FOR ZIMPAPERS . . . A refreshing change from the Wild West of podcasts",
        "detail": "B-Metro touts an exclusive interview with Wicknell Chivayo as a major win for traditional media, contrasting it with the podcast landscape.",
        "source": "B-Metro",
        "url": "https://vertexaisearch.cloud.google.com/grounding-api-redirect/AUZIYQGAdkTk1YBnfEbRjj4PzNFuDFH0cs25ZaNVVw15gRbFqkOWxQq5dk5BPm4vTgdYwKCc-JViSGoORsBkPleubOoj2-YUf5PzxthGl1bcU37A8YjPkO6X6aBbm_Ce6CfrVzA=",
        "category": "Zimbabwe",
        "id": "fzix85ywv4v",
        "fetchedAt": "2026-05-07T02:00:17.663Z",
        "date": "2026-05-07"
      },
      {
        "headline": "EDITORIAL COMMENT: CHIVAYO EXCLUSIVE INTERVEW: A MASSIVE COUP FOR TRADITIONAL MEDIA",
        "detail": "B-Metro editorializes on their exclusive interview with Wicknell Chivayo, calling it a major coup for traditional media.",
        "source": "B-Metro",
        "url": "https://vertexaisearch.cloud.google.com/grounding-api-redirect/AUZIYQGAdkTk1YBnfEbRjj4PzNFuDFH0cs25ZaNVVw15gRbFqkOWxQq5dk5BPm4vTgdYwKCc-JViSGoORsBkPleubOoj2-YUf5PzxthGl1bcU37A8YjPkO6X6aBbm_Ce6CfrVzA=",
        "category": "Zimbabwe",
        "id": "wixsb8efone",
        "fetchedAt": "2026-05-07T02:00:17.663Z",
        "date": "2026-05-07"
      },
      {
        "headline": "'WE'RE VERY SORRY, BOSS' . . . CAPS players apologise for Chiefs loss, turn attention to 'Derby De Bus'",
        "detail": "CAPS United players have apologized for their loss to Chiefs and are now focusing on the 'Derby De Bus,' according to B-Metro.",
        "source": "B-Metro",
        "url": "https://vertexaisearch.cloud.google.com/grounding-api-redirect/AUZIYQGAdkTk1YBnfEbRjj4PzNFuDFH0cs25ZaNVVw15gRbFqkOWxQq5dk5BPm4vTgdYwKCc-JViSGoORsBkPleubOoj2-YUf5PzxthGl1bcU37A8YjPkO6X6aBbm_Ce6CfrVzA=",
        "category": "Zimbabwe",
        "id": "ztfja35tbvp",
        "fetchedAt": "2026-05-07T02:00:17.663Z",
        "date": "2026-05-07"
      },
      {
        "headline": "Voice Calls Hit 5.07 Billion Minutes in Zimbabwe as Usage Surges",
        "detail": "Zimbabwe experienced a significant increase in mobile voice usage during the final quarter of 2025, with users spending over 5 billion minutes on calls, despite the global trend towards instant messaging. The Postal and Telecommunications Regulatory Authority of Zimbabwe (POTRAZ) attributes this rise to the growing popularity of affordable on-net bundles and promotional offers.",
        "source": "iHarare News",
        "url": "https://vertexaisearch.cloud.google.com/grounding-api-redirect/AUZIYQGJXOkBhh-mnkhdvMqnhspXWDuXBRs9DQK2E8Wn7hW6zrI1XvCx5__3MU6oDiGgQ9z5Pfz6rdKNr2_nN5izOD4bWsdUCUO3r_-PNwqBRIm30Y_4XBLmSjQjJ7dpY4TYuf2xbGJfiNYZYX9R7Mhu9dkurc4MsJj7SgUVR8RghjodWBH-O1koFerq9bn3nZa84Q==",
        "category": "Zimbabwe",
        "id": "g2y0y0bn7rs",
        "fetchedAt": "2026-05-07T02:00:17.663Z",
        "date": "2026-05-07"
      }
    ]
  }
}